asmk/__init__.py
asmk/asmk_method.py
asmk/codebook.py
asmk/functional.py
asmk/hamming.cp311-win_amd64.pyd
asmk/index.py
asmk/inverted_file.py
asmk/io_helpers.py
asmk/kernel.py
asmk-0.1.1.dist-info/licenses/LICENSE
asmk-0.1.1.dist-info/METADATA
asmk-0.1.1.dist-info/WHEEL
asmk-0.1.1.dist-info/top_level.txt
asmk-0.1.1.dist-info/zip-safe
asmk-0.1.1.dist-info/RECORD
