Metadata-Version: 2.4
Name: asmk
Version: 0.1.1
Summary: Python implementation of ASMK (Aggregated Selective Match Kernels)
Author: Tomas Jenicek, Giorgos Tolias
Maintainer: Zheyuan Wu
License: MIT
Project-URL: Homepage, https://github.com/trance-0/asmk
Project-URL: Documentation, https://arxiv.org/abs/2007.13172
Requires-Python: >=3.6
License-File: LICENSE
Requires-Dist: pyaml
Requires-Dist: numpy
Requires-Dist: faiss-cpu
Dynamic: license-file
